Workbook

Sheet 契約稟議2026
A1: 契 約 稟 議 書
A3: 取引状況 | D3: 有 | N3: 稟議№ | T3: -
A4: 稟議種別 | D4: 既存 | N4: 決裁日
A5: 決済希望スピード | D5: 飛行機 | N5: 申請日 | Q5: 2026 | S5: 年 | T5: 7 | U5: 月 | V5: 28 | W5: 日
A6: 契約の種別 | D6: 人材派遣 | N6: 企業名 | Q6: bring plus | T6: 営業所 | V6: 茨城
A7: 変形労働時間 有/無 | D7: 無 | N7: 申請者 | Q7: 川住 悠希
A8: ■企業情報
A9: 企 業 名 | D9: 第一熱処理工業株式会社 | N9: 工場名 | P9: 成田工場
A10: 住 所 | D10: 〒 | E10: 287-0225 | H10: 千葉県成田市吉岡681-2
A11: 電話番号 | D11: 0476-73-7997 | M11: FAX
A12: 取引企業代表者名 | D12: 曾根光彰 | H12: 窓口担当者⇒ | J12: 部署名 | N12: 役職 | P12: 担当部長 | R12: 名前 | T12: 黒﨑善行
A13: 企業規模 | D13: 資本金 | F13: 3000 | H13: 千万円 | J13: 区分 | L13: 未上場
D14: 創業・設立 | G14: 21903 | L14: 業種 | N14: 生産用機械器具製造業 | S14: 生産品目 | U14: 自動車、建機部品
A15: ■契約内容
A16: 契約部署 | D16: 成田工場 | H16: 作業内容 | J16: 金属製品の検査 | R16: 必要資格 | T16: なし
A17: 契約（予定）日 | D17: 46237 | G17: 契約期間（自） | J17: 46237 | M17: 契約期間（至） | P17: 46285 | S17: 契約更新ヶ月 | U17: 2ヵ月
A18: 欠員・契約人数・工数 | D18: 男性 | E18: 1 | G18: 女性 | H18: 0 | J18: 合計 | K18: =SUM(E18+H18) -> 1 | L18: 入金サイト | N18: 締日 | O18: 20日 | Q18: 入金日 | R18: 翌月20日 | T18: 請求必着日 | V18: 5営業日
A19: 勤務内容 | D19: 勤務時間 | J19: 休憩時間 | M19: 所定労働時間 | P19: 割増請求稼働時間 | S19: 平均稼動日数 | V19: 勤務形態
D20: ① | E20: 0.35416667 | G20: ～ | H20: 0.72916667 | J20: 60 | L20: M | M20: 8 | O20: H | P20: 8 | R20: H超 | S20: 20 | U20: 日 | V20: 日勤
D21: ② | G21: ～ | L21: M | O21: H | R21: H超 | U21: 日 | V21: 日勤
D22: ③ | G22: ～ | L22: M | O22: H | R22: H超 | U22: 日 | V22: 日勤
D23: ④ | G23: ～ | L23: M | O23: H | R23: H超 | U23: 日
A24: 休日 | D24: 土日祝（会社カレンダー有） | J24: 給与支給 | L24: 締日 | N24: 20日 | R24: 支払日 | T24: 翌月15日
A25: ■契約金額／支払単価 /職業分類
A26: 主な作業内容 | D26: 請単価 | F26: 支払単価 | H26: 原価率 | J26: 手当①：名称 | L26: 手当①：支給額 | N26: 手当①：請求額 | P26: 手当②：名称 | R26: 手当②：支給額 | T26: 手当②：請求額 | V26: 交通費（上限）
A27: ① | B27: 一般事務 | D27: 2400 | F27: 1350 | H27: =F27/D27 -> 0.5625 | V27: 13000円
A28: ② | H28: =F28/D28 -> #DIV/0! | V28: 13000円
A29: ③ | H29: =F29/D29 -> #DIV/0!
A30: ④ | H30: =F30/D30 -> #DIV/0!
A31: 割増 | D31: 時間外 | F31: 1.25 | H31: 深夜 | J31: 1.25 | L31: 法定外休出 | N31: 1.25 | P31: 法定外休出 | R31: 1.25 | T31: 時間外６０H超 | V31: 1.5
A32: 職業安定 業務統計 | C32: NO | D32: 小分類 | F32: 職業名 | J32: 地域名 | M32: 基準値（0年） | P32: 地域指数 | R32: 標準基準値×地域指数 | U32: 支払時給との差異
C33: ① | D33: 3401 | F33: =VLOOKUP(D33,職業統計!A3:K440,2,FALSE) -> 一般事務員 | J33: 千葉 | M33: =VLOOKUP(D33,職業統計!A3:K440,3,FALSE) -> 1122 | P33: =VLOOKUP(J33,'別添３（都道府県別）'!C7:D487,2,FALSE)/100 -> 1.067 | R33: =M33*P33 -> 1197.174 | U33: =F27-R33 -> 152.826
C34: ② | F34: =VLOOKUP(D34,職業統計!A4:K441,2,FALSE) -> #N/A | M34: =VLOOKUP(D34,職業統計!A4:K441,3,FALSE) -> #N/A | P34: =VLOOKUP(J34,'別添３（都道府県別）'!C8:D488,2,FALSE)/100 -> #N/A | R34: =M34*P34 -> #N/A | U34: =F28-R34 -> #N/A
C35: ③ | F35: =VLOOKUP(D35,職業統計!A5:K442,2,FALSE) -> #N/A | M35: =VLOOKUP(D35,職業統計!A5:K442,3,FALSE) -> #N/A | P35: =VLOOKUP(J35,'別添３（都道府県別）'!C9:D489,2,FALSE)/100 -> #N/A | R35: =M35*P35 -> #N/A | U35: =F29-R35 -> #N/A
C36: ④ | F36: =VLOOKUP(D36,職業統計!A6:K443,2,FALSE) -> #N/A | M36: =VLOOKUP(D36,職業統計!A6:K443,3,FALSE) -> #N/A | P36: =VLOOKUP(J36,'別添３（都道府県別）'!C10:D490,2,FALSE)/100 -> #N/A | R36: =M36*P36 -> #N/A | U36: =F30-R36 -> #N/A
A38: ■現況及び起案者所見
A39: 事務女性1名の受注。求人依頼・掘起し対応いたします。
A40: ■備考
A41: 現状検査員男性1名の欠員有
A43: ■所長コメント
A45: ■管理本部コメント
A47: 経理所見
A50: 決済ナンバー | I50: 決済 | O50: 経理 | R50: 管理本部 | U50: 所 長
R51: 藤井 | U51: 川住

Sheet 職業統計
A1: 職業安 | K1: 別添２
A3: 201 | B3: 会社管理職員 | C3: 1684 | D3: 1916 | E3: 2051 | F3: 2102 | G3: 2250 | H3: 2403 | I3: 2987 | J3: - | K3: 1949
A4: 299 | B4: その他の法人・団体管理職員 | C4: 1554 | D4: 1768 | E4: 1893 | F4: 1939 | G4: 2076 | H4: 2218 | I4: 2757 | J4: 1563 | K4: 1748
A5: 301 | B5: 管理的公務員 | C5: 1334 | D5: 1518 | E5: 1625 | F5: 1665 | G5: 1782 | H5: 1904 | I5: 2367 | J5: - | K5: 1529
A6: 399 | B6: 他に分類されない管理的職業 | C6: 1447 | D6: 1647 | E6: 1762 | F6: 1806 | G6: 1933 | H6: 2065 | I6: 2567 | J6: - | K6: 1665
A7: 401 | B7: 自然科学系研究者 | C7: 1357 | D7: 1544 | E7: 1653 | F7: 1694 | G7: 1813 | H7: 1936 | I7: 2407 | J7: - | K7: 1627
A8: 402 | B8: 人文・社会科学系等研究者 | C8: - | D8: - | E8: - | F8: - | G8: - | H8: - | I8: - | J8: - | K8: -
A9: 501 | B9: 農林水産技術者 | C9: 1152 | D9: 1311 | E9: 1403 | F9: 1438 | G9: 1539 | H9: 1644 | I9: 2044 | J9: - | K9: 1348
A10: 601 | B10: 食品開発技術者 | C10: 1256 | D10: 1429 | E10: 1530 | F10: 1567 | G10: 1678 | H10: 1792 | I10: 2228 | J10: - | K10: 1471
A11: 602 | B11: 電気・電子・電気通信開発技術者 （通信ネットワークを除く） | C11: 1400 | D11: 1593 | E11: 1705 | F11: 1747 | G11: 1870 | H11: 1998 | I11: 2484 | J11: - | K11: 1820
A12: 603 | B12: 機械開発技術者 | C12: 1350 | D12: 1536 | E12: 1644 | F12: 1685 | G12: 1804 | H12: 1926 | I12: 2395 | J12: - | K12: 1745
A13: 604 | B13: 自動車開発技術者 | C13: 1364 | D13: 1552 | E13: 1661 | F13: 1702 | G13: 1822 | H13: 1946 | I13: 2420 | J13: - | K13: 1784
A14: 605 | B14: 輸送用機器開発技術者（自動車を除く） | C14: 1184 | D14: 1347 | E14: 1442 | F14: 1478 | G14: 1582 | H14: 1690 | I14: 2100 | J14: 1192 | K14: 1501
A15: 606 | B15: 金属製錬・材料開発技術者 | C15: 1301 | D15: 1481 | E15: 1585 | F15: 1624 | G15: 1738 | H15: 1857 | I15: 2308 | J15: - | K15: 1589
A16: 607 | B16: 化学製品開発技術者 | C16: 1355 | D16: 1542 | E16: 1650 | F16: 1691 | G16: 1810 | H16: 1934 | I16: 2404 | J16: - | K16: 1637
A17: 699 | B17: その他の開発技術者 | C17: 1339 | D17: 1524 | E17: 1631 | F17: 1671 | G17: 1789 | H17: 1911 | I17: 2375 | J17: - | K17: 1636
A18: 701 | B18: 食品製造技術者 | C18: 1229 | D18: 1399 | E18: 1497 | F18: 1534 | G18: 1642 | H18: 1754 | I18: 2180 | J18: - | K18: 1409
A19: 702 | B19: 電気・電子・電気通信製造技術者 （通信ネットワーク・電気工事技術者を除く） | C19: 1336 | D19: 1520 | E19: 1627 | F19: 1667 | G19: 1785 | H19: 1906 | I19: 2370 | J19: - | K19: 1653
A20: 703 | B20: 電気工事技術者 | C20: 1426 | D20: 1623 | E20: 1737 | F20: 1780 | G20: 1905 | H20: 2035 | I20: 2530 | J20: - | K20: 1865
A21: 704 | B21: 機械製造技術者 | C21: 1279 | D21: 1456 | E21: 1558 | F21: 1596 | G21: 1709 | H21: 1825 | I21: 2269 | J21: - | K21: 1623
A22: 705 | B22: 自動車製造技術者 | C22: 1267 | D22: 1442 | E22: 1543 | F22: 1581 | G22: 1693 | H22: 1808 | I22: 2248 | J22: - | K22: 1577
A23: 706 | B23: 輸送用機器製造技術者（自動車を除く） | C23: 1215 | D23: 1383 | E23: 1480 | F23: 1516 | G23: 1623 | H23: 1734 | I23: 2155 | J23: - | K23: 1492
A24: 707 | B24: 金属製錬・材料製造技術者 | C24: 1238 | D24: 1409 | E24: 1508 | F24: 1545 | G24: 1654 | H24: 1767 | I24: 2196 | J24: - | K24: 1501
A25: 708 | B25: 化学製品製造技術者 | C25: 1264 | D25: 1438 | E25: 1540 | F25: 1577 | G25: 1689 | H25: 1804 | I25: 2242 | J25: - | K25: 1513
A26: 799 | B26: その他の製造技術者 | C26: 1238 | D26: 1409 | E26: 1508 | F26: 1545 | G26: 1654 | H26: 1767 | I26: 2196 | J26: - | K26: 1479
... A36: 903 | B36: プログラマー | C36: 1412 | D36: 1607 | E36: 1720 | F36: 1762 | G36: 1886 | H36: 2015 | I36: 2505 | J36: - | K36: 1926
A37: 999 | B37: その他の情報処理・通信技術者（ソフトウェア開発） | C37: 1471 | D37: 1674 | E37: 1792 | F37: 1836 | G37: 1965 | H37: 2099 | I37: 2610 | J37: 1483 | K37: 1917
A38: 1001 | B38: ＩＴコンサルタント | C38: 1499 | D38: 1706 | E38: 1826 | F38: 1871 | G38: 2003 | H38: 2139 | I38: 2659 | J38: - | K38: 2052
A39: 1002 | B39: ＩＴシステム設計技術者 | C39: 1476 | D39: 1680 | E39: 1798 | F39: 1842 | G39: 1972 | H39: 2106 | I39: 2618 | J39: - | K39: 2018
A40: 1003 | B40: ＩＴプロジェクトマネージャ | C40: 1758 | D40: 2001 | E40: 2141 | F40: 2194 | G40: 2349 | H40: 2509 | I40: 3119 | J40: - | K40: 2272
A41: 1004 | B41: ＩＴシステム運用管理者 | C41: 1384 | D41: 1575 | E41: 1686 | F41: 1727 | G41: 1849 | H41: 1975 | I41: 2455 | J41: - | K41: 1833
A42: 1005 | B42: ＩＴヘルプデスク | C42: 1312 | D42: 1493 | E42: 1598 | F42: 1637 | G42: 1753 | H42: 1872 | I42: 2327 | J42: - | K42: 1674
A43: 1006 | B43: 通信ネットワーク技術者 | C43: 1431 | D43: 1628 | E43: 1743 | F43: 1786 | G43: 1912 | H43: 2042 | I43: 2539 | J43: - | K43: 1933
A44: 1099 | B44: その他の情報処理・通信技術者 （ソフトウェア開発を除く） | C44: 1426 | D44: 1623 | E44: 1737 | F44: 1780 | G44: 1905 | H44: 2035 | I44: 2530 | J44: - | K44: 1907
A45: 1101 | B45: 通信機器操作員 | C45: 1204 | D45: 1370 | E45: 1466 | F45: 1503 | G45: 1609 | H45: 1718 | I45: 2136 | J45: - | K45: 1397
A46: 1199 | B46: 他に分類されない技術の職業 | C46: 1397 | D46: 1590 | E46: 1702 | F46: 1743 | G46: 1866 | H46: 1994 | I46: 2478 | J46: - | K46: 1677
A47: 1201 | B47: 裁判官、検察官、弁護士 | C47: - | D47: - | E47: - | F47: - | G47: - | H47: - | I47: - | J47: - | K47: -
A48: 1202 | B48: 弁理士 | C48: 1372 | D48: 1561 | E48: 1671 | F48: 1712 | G48: 1833 | H48: 1958 | I48: 2434 | J48: 1389 | K48: 2267
A49: 1203 | B49: 司法書士 | C49: 1544 | D49: 1757 | E49: 1881 | F49: 1927 | G49: 2063 | H49: 2203 | I49: 2739 | J49: - | K49: 1877
A50: 1299 | B50: その他の法務の職業 | C50: 1377 | D50: 1567 | E50: 1677 | F50: 1718 | G50: 1840 | H50: 1965 | I50: 2443 | J50: - | K50: 1686
A51: 1301 | B51: 公認会計士 | C51: 1727 | D51: 1965 | E51: 2103 | F51: 2155 | G51: 2307 | H51: 2464 | I51: 3064 | J51: 1863 | K51: 2396
A52: 1302 | B52: 税理士 | C52: 1549 | D52: 1763 | E52: 1887 | F52: 1933 | G52: 2069 | H52: 2210 | I52: 2748 | J52: - | K52: 2049
A53: 1303 | B53: 社会保険労務士 | C53: 1397 | D53: 1590 | E53: 1702 | F53: 1743 | G53: 1866 | H53: 1994 | I53: 2478 | J53: - | K53: 1667
A54: 1399 | B54: その他の経営・金融・保険の専門的職業 | C54: 1367 | D54: 1556 | E54: 1665 | F54: 1706 | G54: 1826 | H54: 1951 | I54: 2425 | J54: - | K54: 1650
A55: 1401 | B55: 宗教家 | C55: 1273 | D55: 1449 | E55: 1551 | F55: 1589 | G55: 1701 | H55: 1817 | I55: 2258 | J55: 1275 | K55: 1406
A56: 1501 | B56: 著述家（翻訳家を除く） | C56: 1324 | D56: 1507 | E56: 1613 | F56: 1652 | G56: 1769 | H56: 1889 | I56: 2349 | J56: - | K56: 1654
A57: 1502 | B57: 翻訳家 | C57: 1277 | D57: 1453 | E57: 1555 | F57: 1594 | G57: 1706 | H57: 1822 | I57: 2265 | J57: - | K57: 1896
A58: 1503 | B58: 記者、編集者 | C58: 1246 | D58: 1418 | E58: 1518 | F58: 1555 | G58: 1665 | H58: 1778 | I58: 2210 | J58: - | K58: 1468
A59: 1601 | B59: 美術家、イラストレーター | C59: 1195 | D59: 1360 | E59: 1456 | F59: 1491 | G59: 1597 | H59: 1705 | I59: 2120 | J59: - | K59: 1397
A60: 1602 | B60: 写真家、映像撮影者 | C60: 1195 | D60: 1360 | E60: 1456 | F60: 1491 | G60: 1597 | H60: 1705 | I60: 2120 | J60: - | K60: 1377
A61: 1701 | B61: ウェブデザイナー | C61: 1288 | D61: 1466 | E61: 1569 | F61: 1607 | G61: 1721 | H61: 1838 | I61: 2285 | J61: - | K61: 1617
A62: 1702 | B62: グラフィックデザイナー | C62: 1240 | D62: 1411 | E62: 1510 | F62: 1548 | G62: 1657 | H62: 1769 | I62: 2200 | J62: - | K62: 1499
A63: 1799 | B63: その他のデザイナー | C63: 1289 | D63: 1467 | E63: 1570 | F63: 1609 | G63: 1722 | H63: 1839 | I63: 2287 | J63: - | K63: 1559
A64: 1801 | B64: 音楽家 | C64: 1173 | D64: 1335 | E64: 1429 | F64: 1464 | G64: 1567 | H64: 1674 | I64: 2081 | J64: - | K64: 1395
A65: 1802 | B65: 舞踊家、俳優、演芸家 | C65: 1111 | D65: 1264 | E65: 1353 | F65: 1387 | G65: 1484 | H65: 1585 | I65: 1971 | J65: 1119 | K65: 1304
A66: 1803 | B66: プロデューサー、演出家 | C66: 1274 | D66: 1450 | E66: 1552 | F66: 1590 | G66: 1702 | H66: 1818 | I66: 2260 | J66: - | K66: 1563
A67: 1901 | B67: 図書館司書 | C67: 1166 | D67: 1327 | E67: 1420 | F67: 1455 | G67: 1558 | H67: 1664 | I67: 2068 | J67: - | K67: 1266
A68: 1902 | B68: 学芸員 | C68: 1253 | D68: 1426 | E68: 1526 | F68: 1564 | G68: 1674 | H68: 1788 | I68: 2223 | J68: - | K68: 1354
A69: 1903 | B69: カウンセラー（医療・福祉施設を除く） | C69: 1396 | D69: 1589 | E69: 1700 | F69: 1742 | G69: 1865 | H69: 1992 | I69: 2477 | J69: - | K69: 1538
A70: 2001 | B70: 職業スポーツ家 | C70: - | D70: - | E70: - | F70: - | G70: - | H70: - | I70: - | J70: - | K70: -
A71: 2002 | B71: 通訳 | C71: 1241 | D71: 1412 | E71: 1512 | F71: 1549 | G71: 1658 | H71: 1771 | I71: 2202 | J71: - | K71: 1430
A72: 2099 | B72: 他に分類されない法務・経営・ 文化芸術等の専門的職業 | C72: 1356 | D72: 1543 | E72: 1652 | F72: 1692 | G72: 1812 | H72: 1935 | I72: 2406 | J72: - | K72: 1648
A73: 2101 | B73: 医師 | C73: 5751 | D73: 6545 | E73: 7005 | F73: 7177 | G73: 7683 | H73: 8207 | I73: 10202 | J73: 5812 | K73: 6592
A74: 2102 | B74: 歯科医師 | C74: 2814 | D74: 3202 | E74: 3427 | F74: 3512 | G74: 3760 | H74: 4016 | I74: 4992 | J74: - | K74: 3907
A75: 2103 | B75: 獣医師 | C75: 1681 | D75: 1913 | E75: 2047 | F75: 2098 | G75: 2246 | H75: 2399 | I75: 2982 | J75: - | K75: 2046
A76: 2104 | B76: 薬剤師 | C76: 1814 | D76: 2064 | E76: 2209 | F76: 2264 | G76: 2424 | H76: 2589 | I76: 3218 | J76: - | K76: 2107
A77: 2201 | B77: 保健師 | C77: 1356 | D77: 1543 | E77: 1652 | F77: 1692 | G77: 1812 | H77: 1935 | I77: 2406 | J77: - | K77: 1520
A78: 2202 | B78: 助産師 | C78: 1511 | D78: 1720 | E78: 1840 | F78: 1886 | G78: 2019 | H78: 2156 | I78: 2681 | J78: - | K78: 1731
A79: 2301 | B79: 看護師・准看護師（病院・診療所） | C79: 1304 | D79: 1484 | E79: 1588 | F79: 1627 | G79: 1742 | H79: 1861 | I79: 2313 | J79: - | K79: 1483
A80: 2302 | B80: 看護師・准看護師（介護施設） | C80: 1361 | D80: 1549 | E80: 1658 | F80: 1699 | G80: 1818 | H80: 1942 | I80: 2414 | J80: - | K80: 1513
A81: 2303 | B81: 看護師・准看護師（訪問看護） | C81: 1578 | D81: 1796 | E81: 1922 | F81: 1969 | G81: 2108 | H81: 2252 | I81: 2799 | J81: - | K81: 1733
A82: 2399 | B82: その他の看護師・准看護師 | C82: 1370 | D82: 1559 | E82: 1669 | F82: 1710 | G82: 1830 | H82: 1955 | I82: 2430 | J82: - | K82: 1495
A83: 2401 | B83: 診療放射線技師 | C83: 1337 | D83: 1522 | E83: 1628 | F83: 1669 | G83: 1786 | H83: 1908 | I83: 2372 | J83: - | K83: 1523
A84: 2402 | B84: 臨床工学技士 | C84: 1257 | D84: 1430 | E84: 1531 | F84: 1569 | G84: 1679 | H84: 1794 | I84: 2230 | J84: - | K84: 1440
A85: 2403 | B85: 臨床検査技師 | C85: 1257 | D85: 1430 | E85: 1531 | F85: 1569 | G85: 1679 | H85: 1794 | I85: 2230 | J85: - | K85: 1427
... A106: 3101 | B106: 小学校教員 | C106: 1259 | D106: 1433 | E106: 1533 | F106: 1571 | G106: 1682 | H106: 1797 | I106: 2233 | J106: - | K106: 1454
A107: 3102 | B107: 中学校教員 | C107: 1163 | D107: 1323 | E107: 1417 | F107: 1451 | G107: 1554 | H107: 1660 | I107: 2063 | J107: 1213 | K107: 1454
A108: 3103 | B108: 義務教育学校教員 | C108: - | D108: - | E108: - | F108: - | G108: - | H108: - | I108: - | J108: - | K108: -
A109: 3104 | B109: 高等学校教員 | C109: 1252 | D109: 1425 | E109: 1525 | F109: 1562 | G109: 1673 | H109: 1787 | I109: 2221 | J109: - | K109: 1449
A110: 3105 | B110: 中等教育学校教員 | C110: - | D110: - | E110: - | F110: - | G110: - | H110: - | I110: - | J110: - | K110: -
A111: 3106 | B111: 特別支援学校教員 | C111: 1212 | D111: 1379 | E111: 1476 | F111: 1513 | G111: 1619 | H111: 1730 | I111: 2150 | J111: - | K111: 1382
A112: 3107 | B112: 高等専門学校教員、大学教員 | C112: 1270 | D112: 1445 | E112: 1547 | F112: 1585 | G112: 1697 | H112: 1812 | I112: 2253 | J112: 1417 | K112: 1579
A113: 3199 | B113: その他の学校等教員 | C113: 1263 | D113: 1437 | E113: 1538 | F113: 1576 | G113: 1687 | H113: 1802 | I113: 2241 | J113: - | K113: 1467
A114: 3201 | B114: 学習・語学指導教師 | C114: 1294 | D114: 1473 | E114: 1576 | F114: 1615 | G114: 1729 | H114: 1847 | I114: 2296 | J114: - | K114: 1479
A115: 3202 | B115: スポーツ・舞踊指導員 | C115: 1219 | D115: 1387 | E115: 1485 | F115: 1521 | G115: 1629 | H115: 1740 | I115: 2163 | J115: - | K115: 1331
A116: 3203 | B116: 趣味・習い事指導教師 | C116: 1237 | D116: 1408 | E116: 1507 | F116: 1544 | G116: 1653 | H116: 1765 | I116: 2194 | J116: - | K116: 1346
A117: 3301 | B117: 総務事務員 | C117: 1203 | D117: 1369 | E117: 1465 | F117: 1501 | G117: 1607 | H117: 1717 | I117: 2134 | J117: - | K117: 1377
A118: 3302 | B118: 人事事務員 | C118: 1328 | D118: 1511 | E118: 1618 | F118: 1657 | G118: 1774 | H118: 1895 | I118: 2356 | J118: - | K118: 1537
A119: 3303 | B119: 企画・調査事務員 | C119: 1334 | D119: 1518 | E119: 1625 | F119: 1665 | G119: 1782 | H119: 1904 | I119: 2367 | J119: - | K119: 1580
A120: 3401 | B120: 一般事務員 | C120: 1122 | D120: 1277 | E120: 1367 | F120: 1400 | G120: 1499 | H120: 1601 | I120: 1990 | J120: - | K120: 1244
A121: 3402 | B121: 秘書 | C121: 1315 | D121: 1496 | E121: 1602 | F121: 1641 | G121: 1757 | H121: 1877 | I121: 2333 | J121: - | K121: 1537
A122: 3403 | B122: 受付・案内事務員 | C122: 1157 | D122: 1317 | E122: 1409 | F122: 1444 | G122: 1546 | H122: 1651 | I122: 2053 | J122: - | K122: 1290
A123: 3501 | B123: 法務・広報・知的財産事務の職業 | C123: 1327 | D123: 1510 | E123: 1616 | F123: 1656 | G123: 1773 | H123: 1894 | I123: 2354 | J123: - | K123: 1584
A124: 3599 | B124: 他に分類されない総務等事務の職業 | C124: 1226 | D124: 1395 | E124: 1493 | F124: 1530 | G124: 1638 | H124: 1750 | I124: 2175 | J124: - | K124: 1403
... A195: 4910 | B195: 福祉用具専門相談員 | C195: 1258 | D195: 1432 | E195: 1532 | F195: 1570 | G195: 1681 | H195: 1795 | I195: 2232 | J195: - | K195: 1403
A196: 4999 | B196: その他の福祉・介護の専門的職業 | C196: 1262 | D196: 1436 | E196: 1537 | F196: 1575 | G196: 1686 | H196: 1801 | I196: 2239 | J196: 1295 | K196: 1405
A197: 5001 | B197: 高齢者入所型施設介護員 | C197: 1183 | D197: 1346 | E197: 1441 | F197: 1476 | G197: 1580 | H197: 1688 | I197: 2099 | J197: - | K197: 1298
A198: 5002 | B198: 高齢者通所型施設介護員 | C198: 1180 | D198: 1343 | E198: 1437 | F198: 1473 | G198: 1576 | H198: 1684 | I198: 2093 | J198: - | K198: 1293
A199: 5003 | B199: 障害者福祉施設介護員 | C199: 1221 | D199: 1389 | E199: 1487 | F199: 1524 | G199: 1631 | H199: 1742 | I199: 2166 | J199: - | K199: 1354
A200: 5099 | B200: その他の施設介護の職業 | C200: 1124 | D200: 1279 | E200: 1369 | F200: 1403 | G200: 1502 | H200: 1604 | I200: 1994 | J200: - | K200: 1225
...

Sheet 別添３（都道府県別）
E1: 別添３
B2: 職業安定業務統計による地域指数
D3: 都道府県別地域指数（※）
C5: 全国計 | D5: 100
C7: 北海道 | D7: 94.8
C8: 青森 | D8: 85.4
C9: 岩手 | D9: 87.7
C10: 宮城 | D10: 96.3
C11: 秋田 | D11: 86.9
C12: 山形 | D12: 89.2
C13: 福島 | D13: 92.5
C14: 茨城 | D14: 101
C15: 栃木 | D15: 99.6
C16: 群馬 | D16: 99
C17: 埼玉 | D17: 107.2
... C487: 八重山計 | D487: 88.4

Sheet リスト
B2: 業種
B3: 食料品製造業
B4: 飲料・たばこ・飼料製造業
B5: 繊維工業
B6: 木材・木製品製造業（家具を除く）
B7: 家具・装備品製造業
B8: パルプ・紙・紙加工品製造業
B9: 印刷・同関連業
B10: 化学工業
B11: 石油製品・石炭製品製造業
B12: プラスチック製品製造業（別掲を除く）
B13: ゴム製品製造業
... B27: その他の業種
